odf/sbe/__init__.py
odf/sbe/accessors.py
odf/sbe/channels.py
odf/sbe/io.py
odf/sbe/parsers.py
odf/sbe/py.typed
odf/sbe/tests/__init__.py
odf/sbe/tests/test_channels.py
odf/sbe/tests/test_io.py
odf/sbe/tests/data/00101.XMLCON
odf/sbe/tests/data/00101.bl
odf/sbe/tests/data/00101.hdr
odf/sbe/tests/data/00101.hex
odf/sbe/tests/data/00101.nc
odf/sbe/tests/data/readme
odf_sbe-0.3.0.dist-info/METADATA
odf_sbe-0.3.0.dist-info/WHEEL
odf_sbe-0.3.0.dist-info/top_level.txt
odf_sbe-0.3.0.dist-info/RECORD
