Metadata-Version: 2.4
Name: odf.sbe
Version: 0.3.0
Summary: A tool for converting SeaBird .HEX data to engineering units
Project-URL: Documentation, https://sio-odf.github.io/odfsbe/
Project-URL: Repository, https://github.com/SIO-ODF/odfsbe.git
Requires-Python: >=3.12
Requires-Dist: netcdf4>=1.7.2
Requires-Dist: xarray
